pipnet/LandmarkProcessor.py
pipnet/__init__.py
pipnet-0.1.0.dist-info/METADATA
pipnet-0.1.0.dist-info/WHEEL
pipnet-0.1.0.dist-info/top_level.txt
pipnet-0.1.0.dist-info/RECORD
