Metadata-Version: 2.1
Name: pipnet
Version: 0.1.0
Summary: A package for PIPNet - landmark prediction using ResNet and MobileNet models
Home-page: https://github.com/datvtn/PIPNet
Author: Dat Viet Thanh Nguyen
Author-email: thanhdatnv2712@gmail.com
Classifier: Programming Language :: Python :: 3
Classifier: License :: OSI Approved :: MIT License
Classifier: Operating System :: OS Independent
Requires-Python: >=3.8
Requires-Dist: torch
Requires-Dist: torchvision
Requires-Dist: opencv-python==4.10.0.84
Requires-Dist: numpy==1.24.3
Requires-Dist: Pillow==10.4.0
Provides-Extra: dev
Requires-Dist: pytest; extra == "dev"
Requires-Dist: black; extra == "dev"
